{
	"name": "DS_dynamic_conn_string",
	"properties": {
		"linkedServiceName": {
			"referenceName": "LS_dynamic_conn_string",
			"type": "LinkedServiceReference",
			"parameters": {
				"param_server_name": "NA",
				"database_name": "NADB",
				"username": "NA"
			}
		},
		"parameters": {
			"param_dataset_schemaname": {
				"type": "String"
			},
			"dataset_param_tablename": {
				"type": "String"
			}
		},
		"annotations": [],
		"type": "AzureSqlTable",
		"schema": [],
		"typeProperties": {
			"schema": {
				"value": "@dataset().param_dataset_schemaname",
				"type": "Expression"
			},
			"table": {
				"value": "@dataset().dataset_param_tablename",
				"type": "Expression"
			}
		}
	}
}